Metadata-Version: 2.1
Name: azazelutils
Version: 0.0.1
Summary: Say Hello!
License: UNKNOWN
Platform: UNKNOWN
